graphsense_lib-2.8.12.dist-info/licenses/LICENSE
graphsenselib/__init__.py
graphsenselib/cli/__init__.py
graphsenselib/cli/common.py
graphsenselib/cli/main.py
graphsenselib/config/__init__.py
graphsenselib/config/cassandra_async_config.py
graphsenselib/config/cli.py
graphsenselib/config/config.py
graphsenselib/config/errors.py
graphsenselib/config/tagstore_config.py
graphsenselib/convert/__init__.py
graphsenselib/convert/accountsetl.py
graphsenselib/convert/cli.py
graphsenselib/datatypes/__init__.py
graphsenselib/datatypes/abi.py
graphsenselib/datatypes/address.py
graphsenselib/datatypes/common.py
graphsenselib/datatypes/errors.py
graphsenselib/datatypes/transactionhash.py
graphsenselib/db/__init__.py
graphsenselib/db/account.py
graphsenselib/db/analytics.py
graphsenselib/db/cassandra.py
graphsenselib/db/cli.py
graphsenselib/db/factory.py
graphsenselib/db/trace.py
graphsenselib/db/utxo.py
graphsenselib/db/asynchronous/__init__.py
graphsenselib/db/asynchronous/cassandra.py
graphsenselib/db/asynchronous/services/__init__.py
graphsenselib/db/asynchronous/services/addresses_service.py
graphsenselib/db/asynchronous/services/blocks_service.py
graphsenselib/db/asynchronous/services/common.py
graphsenselib/db/asynchronous/services/entities_service.py
graphsenselib/db/asynchronous/services/general_service.py
graphsenselib/db/asynchronous/services/rates_service.py
graphsenselib/db/asynchronous/services/stats_service.py
graphsenselib/db/asynchronous/services/tags_service.py
graphsenselib/db/asynchronous/services/tokens_service.py
graphsenselib/db/asynchronous/services/txs_service.py
graphsenselib/db/asynchronous/services/models/__init__.py
graphsenselib/defi/__init__.py
graphsenselib/defi/conversions.py
graphsenselib/defi/models.py
graphsenselib/defi/swaps.py
graphsenselib/defi/bridging/__init__.py
graphsenselib/defi/bridging/models.py
graphsenselib/defi/bridging/symbiosis.py
graphsenselib/defi/bridging/thorchain.py
graphsenselib/defi/swapping/__init__.py
graphsenselib/defi/swapping/models.py
graphsense_lib-2.8.12.dist-info/METADATA
graphsense_lib-2.8.12.dist-info/WHEEL
graphsense_lib-2.8.12.dist-info/entry_points.txt
graphsense_lib-2.8.12.dist-info/top_level.txt
graphsense_lib-2.8.12.dist-info/zip-safe
graphsense_lib-2.8.12.dist-info/RECORD
