Metadata-Version: 2.4
Name: graphsense-lib
Version: 2.8.12
Summary: Graphsense backend lib and automation cli
Author-email: Iknaio Cryptoasset Analytics GmbH <contact@ikna.io>
Project-URL: Homepage, https://graphsense.github.io/
Project-URL: Source, https://github.com/graphsense/graphsense-lib
Project-URL: Changelog, https://github.com/graphsense/graphsense-lib/blob/master/CHANGELOG.md
Project-URL: Tracker, https://github.com/graphsense/graphsense-lib/issues
Project-URL: Download, https://github.com/graphsense
Keywords: graphsense
Platform: any
Classifier: Programming Language :: Python
Classifier: Programming Language :: Python :: 3.9
Classifier: Programming Language :: Python :: 3.10
Classifier: Programming Language :: Python :: 3.11
Classifier: Intended Audience :: Developers
Classifier: Topic :: Utilities
Requires-Python: <3.12,>=3.9
License-File: LICENSE
Requires-Dist: setuptools<80.9,>=80.0.0
Requires-Dist: importlib-metadata; python_version < "3.8"
Requires-Dist: filelock>=3.8.0
Requires-Dist: click>=8.0.3
Requires-Dist: pandas>=1.4.1
Requires-Dist: methodtools>=0.4
Requires-Dist: simplejson>=3.17.6
Requires-Dist: goodconf[yaml]>=3.0.0
Requires-Dist: pydantic>=2.0.0
Requires-Dist: requests>=2.28.1
Requires-Dist: parsy<3.0,>=2.0
Requires-Dist: rich>=12.6.0
Requires-Dist: cashaddress>=1.0.6
Requires-Dist: base58>=2.1
Requires-Dist: bitarray>=2.9
Requires-Dist: eth-event>=1.2.3
Requires-Dist: eth-hash>=0.3.0
Requires-Dist: cassandra-driver>=3.27.0
Requires-Dist: async-lru>=2.0.4
Requires-Dist: aiohttp>=3.8.0
Requires-Dist: tenacity>=8.2.3
Requires-Dist: coincurve>=21.0.0
Requires-Dist: bech32>=1.2.0
Requires-Dist: httpx>=0.28.1
Requires-Dist: ecdsa>=0.13
Requires-Dist: eth-account>=0.13.7
Provides-Extra: ingest
Requires-Dist: graphsense-ethereum-etl>=2.4.6; extra == "ingest"
Requires-Dist: chainside-btcpy>=0.6; extra == "ingest"
Requires-Dist: graphsense-bitcoin-etl>=1.5.5; extra == "ingest"
Requires-Dist: lz4>=4.3.2; extra == "ingest"
Requires-Dist: pyarrow>=16.0.0; extra == "ingest"
Requires-Dist: deltalake>=1.2.1; extra == "ingest"
Requires-Dist: duckdb>=1.0.0; extra == "ingest"
Requires-Dist: grpcio>=1.49.0; extra == "ingest"
Provides-Extra: conversions
Requires-Dist: networkx>=3.2.1; extra == "conversions"
Requires-Dist: matplotlib; extra == "conversions"
Provides-Extra: tagpacks
Requires-Dist: anytree>=2.9.0; extra == "tagpacks"
Requires-Dist: asyncpg>=0.30.0; extra == "tagpacks"
Requires-Dist: colorama>=0.4.6; extra == "tagpacks"
Requires-Dist: fastapi[all]>=0.115.0; extra == "tagpacks"
Requires-Dist: httpx<1.0.0; extra == "tagpacks"
Requires-Dist: gitpython>=3.1; extra == "tagpacks"
Requires-Dist: giturlparse>=0.10; extra == "tagpacks"
Requires-Dist: lz4>=4.3.2; extra == "tagpacks"
Requires-Dist: psycopg2-binary>=2.9.3; extra == "tagpacks"
Requires-Dist: python-dotenv>=1.0.1; extra == "tagpacks"
Requires-Dist: pyyaml-include~=1.3; extra == "tagpacks"
Requires-Dist: pyyaml>=6.0; extra == "tagpacks"
Requires-Dist: sqlmodel>=0.0.22; extra == "tagpacks"
Requires-Dist: tabulate>=0.9.0; extra == "tagpacks"
Requires-Dist: rapidfuzz>=3.13.0; extra == "tagpacks"
Requires-Dist: rapidyaml>=0.10.0; extra == "tagpacks"
Provides-Extra: all
Requires-Dist: graphsense-lib[ingest]; extra == "all"
Requires-Dist: graphsense-lib[conversions]; extra == "all"
Requires-Dist: graphsense-lib[tagpacks]; extra == "all"
Dynamic: license-file
